cq_annotate/__init__.py
cq_annotate/callouts.py
cq_annotate/dimensioning.py
cq_annotate/overlays.py
cq_annotate/views.py
cq_annotate/icons/safety_warning.svg
cq_annotate-1.2.0.dist-info/METADATA
cq_annotate-1.2.0.dist-info/WHEEL
cq_annotate-1.2.0.dist-info/licenses/LICENSE
cq_annotate-1.2.0.dist-info/RECORD
