Metadata-Version: 2.4
Name: cq-annotate
Version: 1.2.0
Summary: An annotation extension designed to work with the CadQuery API
Project-URL: Homepage, https://github.com/jmwright/cq-annotate
Project-URL: Bug Tracker, https://github.com/jmwright/cq-annotate/issues
Author: Jeremy Wright
License-Expression: Apache-2.0
License-File: LICENSE
Classifier: Operating System :: OS Independent
Classifier: Programming Language :: Python :: 3
Requires-Python: >=3.9
Requires-Dist: cadquery
Requires-Dist: svgutils
Provides-Extra: dev
Requires-Dist: black; extra == 'dev'
Requires-Dist: pytest; extra == 'dev'
